linking/__init__.py
linking/main.py
entity_linking_alpha_v1-0.0.1.dist-info/LICENSE.txt
entity_linking_alpha_v1-0.0.1.dist-info/METADATA
entity_linking_alpha_v1-0.0.1.dist-info/WHEEL
entity_linking_alpha_v1-0.0.1.dist-info/top_level.txt
entity_linking_alpha_v1-0.0.1.dist-info/RECORD
