Metadata-Version: 2.1
Name: entity-linking-alpha-v1
Version: 0.0.1
Summary: A library for entity linking
Author: Nikolas
Requires-Python: >=3.10
License-File: LICENSE.txt
Requires-Dist: numpy==1.26.4
Requires-Dist: SPARQLWrapper==2.0.0
Requires-Dist: sentence-transformers==3.1.1
Requires-Dist: aiohttp==3.9.5
Requires-Dist: openai==1.54.2
Requires-Dist: beautifulsoup4==4.12.2
Requires-Dist: fake-useragent==1.5.1
